example/__init__.py
example/helloworld.py
example/oneinstance.py
jobslib/__init__.py
jobslib/cmdlineparser.py
jobslib/config.py
jobslib/context.py
jobslib/exceptions.py
jobslib/imports.py
jobslib/logging.py
jobslib/main.py
jobslib/tasks.py
jobslib/time.py
jobslib/version.py
jobslib/liveness/__init__.py
jobslib/liveness/consul.py
jobslib/liveness/dummy.py
jobslib/metrics/__init__.py
jobslib/metrics/dummy.py
jobslib/metrics/influxdb.py
jobslib/oneinstance/__init__.py
jobslib/oneinstance/consul.py
jobslib/oneinstance/dummy.py
tests/__init__.py
tests/test_cmdlineparser.py
tests/test_config.py
jobslib-3.2.1.dist-info/LICENSE
jobslib-3.2.1.dist-info/METADATA
jobslib-3.2.1.dist-info/WHEEL
jobslib-3.2.1.dist-info/entry_points.txt
jobslib-3.2.1.dist-info/top_level.txt
jobslib-3.2.1.dist-info/zip-safe
jobslib-3.2.1.dist-info/RECORD
