Metadata-Version: 2.1
Name: jobslib
Version: 3.2.1
Summary: Library for launching tasks in parallel environment
Home-page: https://github.com/seznam/jobslib.git
Author: Seznam.cz a.s.
Author-email: doporucovani-vyvoj@firma.seznam.cz
License: BSD
Project-URL: Documentation, https://seznam.github.io/jobslib/
Platform: any
Classifier: Programming Language :: Python :: 3.7
Classifier: Programming Language :: Python :: 3.8
Classifier: Programming Language :: Python :: 3.9
Classifier: Programming Language :: Python :: 3.10
Classifier: License :: OSI Approved :: BSD License
Classifier: Operating System :: OS Independent
Classifier: Intended Audience :: Developers
Classifier: Topic :: Software Development :: Libraries :: Python Modules
License-File: LICENSE
Requires-Dist: cached-property
Requires-Dist: colored
Requires-Dist: influxdb
Requires-Dist: objectvalidator
Requires-Dist: python-consul2
Requires-Dist: retrying
